example_package/__init__.py
example_package/main.py
example_package/print_env.py
example_package/print_text.py
example_package/service_function.py
example_pkg_fajitas30-0.0.7.dist-info/LICENSE
example_pkg_fajitas30-0.0.7.dist-info/METADATA
example_pkg_fajitas30-0.0.7.dist-info/WHEEL
example_pkg_fajitas30-0.0.7.dist-info/top_level.txt
example_pkg_fajitas30-0.0.7.dist-info/RECORD
