Metadata-Version: 2.1
Name: example-pkg-fajitas30
Version: 0.0.7
Summary: A small example package to test the pypi upload
Author: fajitas30
Author-email: maxime.renac@gmail.com
Classifier: Programming Language :: Python :: 3
Classifier: License :: OSI Approved :: MIT License
Classifier: Operating System :: OS Independent
Requires-Python: >=3.6
License-File: LICENSE
